{
    "vector_of_combination": {
        "energy": 3347.097142857143,
        "serine": 4.249714285714286,
        "omega_3": 2.035142857142857,
        "omega_6": 6.436428571428572,
        "omega_9": 8.270428571428571,
        "potassium": 5756.721428571429,
        "calcium": 1140.34,
        "magnesium": 538.9157142857142,
        "sodium": 3946.9500000000003,
        "phosphorus": 1908.4942857142855,
        "iron": 24.25228571428571,
        "manganese": 9.837,
        "copper": 2504.924285714286,
        "selen": 145.88000000000002,
        "zinc": 11.577714285714285,
        "cobalt": 49.402857142857144,
        "molybdenum": 120.02857142857142,
        "chrome": 50.368571428571435,
        "iodine": 406.53999999999996,
        "vitamin_a": 1414.4014285714288,
        "vitamin_b1": 2.5414285714285714,
        "vitamin_b2": 3.925,
        "vitamin_b5": 6.944428571428572,
        "vitamin_b6": 2.418142857142857,
        "vitamin_b9": 741.9228571428572,
        "vitamin_b12": 4.4157142857142855,
        "vitamin_c": 264.15285714285716,
        "vitamin_k": 279.2528571428572,
        "vitamin_e": 16.594285714285714,
        "beta_carotene": 9.683000000000002
    },
    "score": 29.811886664804153,
    "lower_error": 3,
    "upper_error": 3,
    "days_in_week": [
        {
            "day": {
                "recipes": [
                    {
                        "index": "14450",
                        "count": 3
                    },
                    {
                        "index": "25791",
                        "count": 3
                    },
                    {
                        "index": "24760",
                        "count": 3
                    }
                ],
                "foods": [
                    {
                        "index": "237",
                        "count": 2
                    },
                    {
                        "index": "293",
                        "count": 2
                    },
                    {
                        "index": "373",
                        "count": 1
                    },
                    {
                        "index": "828",
                        "count": 14
                    },
                    {
                        "index": "2303",
                        "count": 1
                    },
                    {
                        "index": "2501",
                        "count": 1
                    },
                    {
                        "index": "2556",
                        "count": 1
                    },
                    {
                        "index": "4481",
                        "count": 1
                    },
                    {
                        "index": "4625",
                        "count": 5
                    },
                    {
                        "index": "6093",
                        "count": 1
                    }
                ],
                "combination": {
                    "energy": 3348.88,
                    "serine": 5.746,
                    "omega_3": 4.26,
                    "omega_6": 6.429,
                    "omega_9": 7.507,
                    "potassium": 4826.17,
                    "calcium": 918.9000000000001,
                    "magnesium": 663.39,
                    "sodium": 5249.930000000001,
                    "phosphorus": 1961.302,
                    "iron": 27.646800000000002,
                    "manganese": 6.6434,
                    "copper": 2709.3100000000004,
                    "selen": 154.42,
                    "zinc": 16.18,
                    "cobalt": 48.0,
                    "molybdenum": 92.9,
                    "chrome": 121.0,
                    "iodine": 107.5,
                    "vitamin_a": 1861.2900000000002,
                    "vitamin_b1": 2.3760000000000003,
                    "vitamin_b2": 1.889,
                    "vitamin_b5": 7.465,
                    "vitamin_b6": 2.931,
                    "vitamin_b9": 495.20000000000005,
                    "vitamin_b12": 3.75,
                    "vitamin_c": 100.49,
                    "vitamin_k": 129.19,
                    "vitamin_e": 14.8,
                    "beta_carotene": 11.869
                },
                "lower_error": 3
            },
            "repeats_in_week": 1
        },
        {
            "day": {
                "recipes": [
                    {
                        "index": "1935",
                        "count": 3
                    },
                    {
                        "index": "17214",
                        "count": 3
                    },
                    {
                        "index": "21890",
                        "count": 3
                    }
                ],
                "foods": [
                    {
                        "index": "828",
                        "count": 13
                    },
                    {
                        "index": "1495",
                        "count": 1
                    },
                    {
                        "index": "1555",
                        "count": 11
                    },
                    {
                        "index": "1798",
                        "count": 3
                    },
                    {
                        "index": "2233",
                        "count": 1
                    },
                    {
                        "index": "2865",
                        "count": 4
                    },
                    {
                        "index": "4699",
                        "count": 2
                    },
                    {
                        "index": "4932",
                        "count": 1
                    },
                    {
                        "index": "5221",
                        "count": 7
                    },
                    {
                        "index": "6093",
                        "count": 58
                    }
                ],
                "combination": {
                    "energy": 3345.52,
                    "serine": 6.3870000000000005,
                    "omega_3": 1.097,
                    "omega_6": 5.625,
                    "omega_9": 7.9670000000000005,
                    "potassium": 5248.860000000001,
                    "calcium": 1080.2,
                    "magnesium": 481.87,
                    "sodium": 5051.78,
                    "phosphorus": 1966.779,
                    "iron": 18.915599999999998,
                    "manganese": 3.6318,
                    "copper": 3499.96,
                    "selen": 121.39,
                    "zinc": 10.05,
                    "cobalt": 27.05,
                    "molybdenum": 58.75,
                    "chrome": 28.95,
                    "iodine": 523.42,
                    "vitamin_a": 1223.64,
                    "vitamin_b1": 2.183,
                    "vitamin_b2": 4.5489999999999995,
                    "vitamin_b5": 8.377,
                    "vitamin_b6": 2.258,
                    "vitamin_b9": 539.87,
                    "vitamin_b12": 4.42,
                    "vitamin_c": 246.63,
                    "vitamin_k": 314.10999999999996,
                    "vitamin_e": 12.920000000000002,
                    "beta_carotene": 6.216
                },
                "lower_error": 3
            },
            "repeats_in_week": 2
        },
        {
            "day": {
                "recipes": [
                    {
                        "index": "14461",
                        "count": 3
                    },
                    {
                        "index": "23139",
                        "count": 3
                    },
                    {
                        "index": "6791",
                        "count": 3
                    },
                    {
                        "index": "14113",
                        "count": 1
                    }
                ],
                "foods": [
                    {
                        "index": "198",
                        "count": 12
                    },
                    {
                        "index": "425",
                        "count": 2
                    },
                    {
                        "index": "828",
                        "count": 10
                    },
                    {
                        "index": "1798",
                        "count": 2
                    },
                    {
                        "index": "2320",
                        "count": 2
                    },
                    {
                        "index": "2526",
                        "count": 3
                    },
                    {
                        "index": "5293",
                        "count": 2
                    },
                    {
                        "index": "6024",
                        "count": 2
                    },
                    {
                        "index": "6093",
                        "count": 3
                    },
                    {
                        "index": "6096",
                        "count": 11
                    },
                    {
                        "index": "6449",
                        "count": 2
                    }
                ],
                "combination": {
                    "energy": 3347.44,
                    "serine": 2.8070000000000004,
                    "omega_3": 1.948,
                    "omega_6": 6.844,
                    "omega_9": 8.613,
                    "potassium": 6243.29,
                    "calcium": 1225.77,
                    "magnesium": 536.3199999999999,
                    "sodium": 3068.79,
                    "phosphorus": 1866.15,
                    "iron": 26.071999999999996,
                    "manganese": 13.738,
                    "copper": 1956.31,
                    "selen": 155.99,
                    "zinc": 11.190999999999999,
                    "cobalt": 60.93,
                    "molybdenum": 157.45,
                    "chrome": 43.42,
                    "iodine": 422.86,
                    "vitamin_a": 1398.06,
                    "vitamin_b1": 2.762,
                    "vitamin_b2": 4.122,
                    "vitamin_b5": 6.098000000000001,
                    "vitamin_b6": 2.37,
                    "vitamin_b9": 904.63,
                    "vitamin_b12": 4.58,
                    "vitamin_c": 313.83000000000004,
                    "vitamin_k": 299.3400000000001,
                    "vitamin_e": 18.880000000000003,
                    "beta_carotene": 10.870000000000001
                },
                "lower_error": 3
            },
            "repeats_in_week": 4
        }
    ]
}